dash_editor
