Metadata-Version: 1.1
Name: dash-editor
Version: 0.0.2
Summary: the chart editor
Home-page: UNKNOWN
Author: kalimuthu periyasamy <1995kalimuthu@gmail.com>
Author-email: UNKNOWN
License: MIT
Platform: UNKNOWN
Classifier: Framework :: Dash
